Workbook

Sheet Monthly_Balances
A1: Period | B1: Income | C1: American Express | D1: Discover | E1: Capital one 1 | F1: Capital one 2 | G1: Barclay/Carnival | H1: Barclay/xbox | I1: US Bank | J1: Wells Fargo 1 | K1: Wells Fargo 2 | L1: Lowes | M1: Bestbuy | N1: Citi Card 1 | O1: Citi Card 2 | P1: Total Debt | Q1: Debt-to-Income Ratio
A2: 45292 | B2: 3800 | C2: 4200 | D2: 2500 | E2: 3100 | F2: 900 | P2: =SUM(C2:O2) -> 10700 | Q2: =Table1[[#This Row],[Total Debt]]/Table1[[#This Row],[Income]] -> 2.8157895
A3: 45323 | B3: 3800 | C3: 4150 | D3: 2450 | E3: 3050 | F3: 850 | P3: =SUM(C3:O3) -> 10500 | Q3: =Table1[[#This Row],[Total Debt]]/Table1[[#This Row],[Income]] -> 2.7631579
A4: 45352 | B4: 3800 | C4: 4050 | D4: 2400 | E4: 2950 | F4: 820 | P4: =SUM(C4:O4) -> 10220 | Q4: =Table1[[#This Row],[Total Debt]]/Table1[[#This Row],[Income]] -> 2.6894737
A5: 45383 | B5: 3900 | C5: 3950 | D5: 2300 | E5: 2850 | F5: 780 | P5: =SUM(C5:O5) -> 9880 | Q5: =Table1[[#This Row],[Total Debt]]/Table1[[#This Row],[Income]] -> 2.5333333
A6: 45413 | B6: 3900 | C6: 3800 | D6: 2200 | E6: 2750 | F6: 750 | P6: =SUM(C6:O6) -> 9500 | Q6: =Table1[[#This Row],[Total Debt]]/Table1[[#This Row],[Income]] -> 2.4358974
A7: 45444 | B7: 3900 | C7: 3700 | D7: 2100 | E7: 2650 | F7: 700 | P7: =SUM(C7:O7) -> 9150 | Q7: =Table1[[#This Row],[Total Debt]]/Table1[[#This Row],[Income]] -> 2.3461538
A8: 45474 | B8: 4000 | C8: 3600 | D8: 2000 | E8: 2550 | F8: 650 | P8: =SUM(C8:O8) -> 8800 | Q8: =Table1[[#This Row],[Total Debt]]/Table1[[#This Row],[Income]] -> 2.2
A9: 45505 | B9: 4000 | C9: 3500 | D9: 1900 | E9: 2450 | F9: 600 | P9: =SUM(C9:O9) -> 8450 | Q9: =Table1[[#This Row],[Total Debt]]/Table1[[#This Row],[Income]] -> 2.1125
A10: 45536 | B10: 4000 | C10: 3400 | D10: 1800 | E10: 2350 | F10: 550 | P10: =SUM(C10:O10) -> 8100 | Q10: =Table1[[#This Row],[Total Debt]]/Table1[[#This Row],[Income]] -> 2.025
A11: 45566 | B11: 4100 | C11: 3250 | D11: 1700 | E11: 2250 | F11: 500 | P11: =SUM(C11:O11) -> 7700 | Q11: =Table1[[#This Row],[Total Debt]]/Table1[[#This Row],[Income]] -> 1.8780488
A12: 45597 | B12: 4100 | C12: 3100 | D12: 1600 | E12: 2150 | F12: 450 | P12: =SUM(C12:O12) -> 7300 | Q12: =Table1[[#This Row],[Total Debt]]/Table1[[#This Row],[Income]] -> 1.7804878
A13: 45627 | B13: 4200 | C13: 3000 | D13: 1500 | E13: 2050 | F13: 400 | P13: =SUM(C13:O13) -> 6950 | Q13: =Table1[[#This Row],[Total Debt]]/Table1[[#This Row],[Income]] -> 1.6547619
... A37: 46357 | B37: 5000 | C37: 100 | D37: 0 | E37: 0 | F37: 0 | P37: =SUM(C37:O37) -> 100 | Q37: =Table1[[#This Row],[Total Debt]]/Table1[[#This Row],[Income]] -> 0.02

Sheet Dashboard
A1: Personal Financial Dashboard
A2: Total Debt | B2: =SUM(Monthly_Balances!P:P) -> 176960
A3: Highest Balance | B3: =MAX(Monthly_Balances!P:P) -> 10700
A4: Lowest Balance | B4: =MIN(Monthly_Balances!P:P) -> 100
A5: Average Debt | B5: =AVERAGE(Monthly_Balances!P:P) -> 4915.5556
A6: Latest Month Debt | B6: {=LOOKUP(2,1/(Monthly_Balances!P:P<>""),Monthly_Balances!P:P)} -> 100
A7: Debt-to-Income Ratio | B7: {=LOOKUP(2,1/(Monthly_Balances!Q:Q<>""),Monthly_Balances!Q:Q)} -> 0.02
